quantstats/__init__.py
quantstats/_compat.py
quantstats/_numpy_compat.py
quantstats/plots.py
quantstats/report.html
quantstats/reports.py
quantstats/stats.py
quantstats/utils.py
quantstats/version.py
quantstats/_plotting/__init__.py
quantstats/_plotting/core.py
quantstats/_plotting/wrappers.py
quantstats-0.0.76.dist-info/licenses/LICENSE.txt
quantstats-0.0.76.dist-info/METADATA
quantstats-0.0.76.dist-info/WHEEL
quantstats-0.0.76.dist-info/entry_points.txt
quantstats-0.0.76.dist-info/top_level.txt
quantstats-0.0.76.dist-info/RECORD
