Metadata-Version: 2.4
Name: QuantStats
Version: 0.0.76
Summary: Portfolio analytics for quants
Home-page: https://github.com/ranaroussi/quantstats
Author: Ran Aroussi
Author-email: ran@aroussi.com
License: Apache Software License
Keywords: quant algotrading algorithmic-trading quantitative-trading
Platform: any
Classifier: License :: OSI Approved :: Apache Software License
Classifier: Development Status :: 5 - Production/Stable
Classifier: Operating System :: OS Independent
Classifier: Intended Audience :: Developers
Classifier: Intended Audience :: Financial and Insurance Industry
Classifier: Intended Audience :: Science/Research
Classifier: Topic :: Office/Business :: Financial
Classifier: Topic :: Office/Business :: Financial :: Investment
Classifier: Topic :: Software Development :: Libraries
Classifier: Topic :: Software Development :: Libraries :: Python Modules
Classifier: Topic :: Scientific/Engineering
Classifier: Topic :: Scientific/Engineering :: Information Analysis
Classifier: Topic :: Scientific/Engineering :: Mathematics
Classifier: Programming Language :: Python :: 3.8
Classifier: Programming Language :: Python :: 3.9
Classifier: Programming Language :: Python :: 3.10
Classifier: Programming Language :: Python :: 3.11
Classifier: Programming Language :: Python :: 3.12
Classifier: Programming Language :: Python :: 3.13
License-File: LICENSE.txt
Requires-Dist: pandas<3.0.0,>=1.5.0
Requires-Dist: numpy>=1.21.0
Requires-Dist: seaborn>=0.11.0
Requires-Dist: matplotlib>=3.3.0
Requires-Dist: scipy>=1.7.0
Requires-Dist: tabulate>=0.8.9
Requires-Dist: yfinance>=0.2.65
Requires-Dist: python-dateutil>=2.8.0
Requires-Dist: packaging>=20.0
Dynamic: author
Dynamic: author-email
Dynamic: classifier
Dynamic: description
Dynamic: home-page
Dynamic: keywords
Dynamic: license
Dynamic: license-file
Dynamic: platform
Dynamic: requires-dist
Dynamic: summary
